docker_gobject/__init__.py
docker_gobject/__main__.py
docker_gobject/authentication.py
docker_gobject/client.py
docker_gobject/container.py
docker_gobject/containers.py
docker_gobject/image.py
docker_gobject/images.py
docker_gobject/monitor.py
docker_gobject/session.py
docker_gobject/.vscode/settings.json
docker_gobject-0.0.2.dist-info/METADATA
docker_gobject-0.0.2.dist-info/WHEEL
docker_gobject-0.0.2.dist-info/top_level.txt
docker_gobject-0.0.2.dist-info/RECORD
