Metadata-Version: 2.1
Name: docker-gobject
Version: 0.0.2
Summary: GObject wrapper for Docker Engine
Author-email: Cameron Dahl <cameron@cameorndahl.com>
Project-URL: Homepage, https://github.com/cameronthecoder/docker_gobject
Project-URL: Bug Tracker, https://github.com/pypa/docker_gobject/issues
Keywords: pygobject,gtk,gtk4,docker,wrapper,python,python3,libsoup,soup,glib
Classifier: Programming Language :: Python :: 3
Classifier: License :: OSI Approved :: MIT License
Classifier: Operating System :: OS Independent
Requires-Python: >=3.7
Requires-Dist: PyGObject
